[{"code":"210422100","name":"新宾镇"},{"code":"210422101","name":"旺清门镇"},{"code":"210422102","name":"永陵镇"},{"code":"210422103","name":"平顶山镇"},{"code":"210422104","name":"大四平镇"},{"code":"210422105","name":"苇子峪镇"},{"code":"210422106","name":"木奇镇"},{"code":"210422108","name":"上夹河镇"},{"code":"210422109","name":"南杂木镇"},{"code":"210422202","name":"红升乡"},{"code":"210422203","name":"响水河子乡"},{"code":"210422204","name":"红庙子乡"},{"code":"210422205","name":"北四平乡"},{"code":"210422207","name":"榆树乡"},{"code":"210422208","name":"下夹河乡"}]