[{"code":"230102001","name":"兆麟街道"},{"code":"230102002","name":"新阳路街道"},{"code":"230102003","name":"抚顺街道"},{"code":"230102004","name":"共乐街道"},{"code":"230102005","name":"新华街道"},{"code":"230102006","name":"城乡路街道"},{"code":"230102007","name":"工农街道"},{"code":"230102008","name":"尚志街道"},{"code":"230102009","name":"斯大林街道"},{"code":"230102010","name":"通江街道"},{"code":"230102011","name":"经纬街道"},{"code":"230102012","name":"工程街道"},{"code":"230102013","name":"安静街道"},{"code":"230102014","name":"安和街道"},{"code":"230102015","name":"正阳河街道"},{"code":"230102016","name":"建国街道"},{"code":"230102017","name":"康安街道"},{"code":"230102018","name":"爱建街道"},{"code":"230102019","name":"群力街道"},{"code":"230102101","name":"太平镇"},{"code":"230102102","name":"新发镇"},{"code":"230102103","name":"新农镇"},{"code":"230102104","name":"榆树镇"},{"code":"230102500","name":"闫家岗农场"},{"code":"230102579","name":"道里区农垦"}]