[{"code":"320923001","name":"阜城街道"},{"code":"320923002","name":"吴滩街道"},{"code":"320923003","name":"花园街道（开发区）"},{"code":"320923004","name":"金沙湖街道"},{"code":"320923100","name":"沟墩镇"},{"code":"320923101","name":"陈良镇"},{"code":"320923102","name":"三灶镇"},{"code":"320923103","name":"郭墅镇（澳洋工业园）"},{"code":"320923104","name":"新沟镇"},{"code":"320923105","name":"陈集镇"},{"code":"320923106","name":"羊寨镇"},{"code":"320923107","name":"芦蒲镇"},{"code":"320923108","name":"板湖镇"},{"code":"320923109","name":"东沟镇"},{"code":"320923110","name":"益林镇"},{"code":"320923111","name":"古河镇"},{"code":"320923112","name":"罗桥镇"},{"code":"320923402","name":"现代服务业园区"}]