[{"code":"330602001","name":"塔山街道"},{"code":"330602002","name":"府山街道"},{"code":"330602003","name":"蕺山街道"},{"code":"330602004","name":"北海街道"},{"code":"330602005","name":"城南街道"},{"code":"330602006","name":"稽山街道"},{"code":"330602007","name":"迪荡街道"},{"code":"330602100","name":"东湖镇"},{"code":"330602101","name":"灵芝镇"},{"code":"330602102","name":"东浦镇"},{"code":"330602103","name":"鉴湖镇"},{"code":"330602104","name":"皋埠镇"},{"code":"330602105","name":"马山镇"},{"code":"330602106","name":"斗门镇"},{"code":"330602107","name":"孙端镇"},{"code":"330602108","name":"富盛镇"},{"code":"330602109","name":"陶堰镇"}]