[{"code":"341226100","name":"慎城镇"},{"code":"341226101","name":"谢桥镇"},{"code":"341226102","name":"南照镇"},{"code":"341226103","name":"杨湖镇"},{"code":"341226104","name":"江口镇"},{"code":"341226105","name":"润河镇"},{"code":"341226106","name":"新集镇"},{"code":"341226107","name":"六十铺镇"},{"code":"341226108","name":"耿棚镇"},{"code":"341226109","name":"半岗镇"},{"code":"341226110","name":"王岗镇"},{"code":"341226111","name":"夏桥镇"},{"code":"341226112","name":"江店孜镇"},{"code":"341226113","name":"陈桥镇"},{"code":"341226114","name":"黄桥镇"},{"code":"341226115","name":"八里河镇"},{"code":"341226116","name":"迪沟镇"},{"code":"341226117","name":"西三十铺镇"},{"code":"341226118","name":"红星镇"},{"code":"341226119","name":"十八里铺镇"},{"code":"341226120","name":"鲁口镇"},{"code":"341226121","name":"古城镇"},{"code":"341226200","name":"建颍乡"},{"code":"341226201","name":"五十铺乡"},{"code":"341226202","name":"盛堂乡"},{"code":"341226203","name":"关屯乡"},{"code":"341226204","name":"垂岗乡"},{"code":"341226205","name":"赛涧回族乡"},{"code":"341226206","name":"刘集乡"},{"code":"341226207","name":"黄坝乡"}]