[{"code":"350122100","name":"凤城镇"},{"code":"350122101","name":"敖江镇"},{"code":"350122102","name":"东岱镇"},{"code":"350122103","name":"琯头镇"},{"code":"350122104","name":"晓澳镇"},{"code":"350122105","name":"东湖镇"},{"code":"350122106","name":"丹阳镇"},{"code":"350122107","name":"长龙镇"},{"code":"350122108","name":"透堡镇"},{"code":"350122109","name":"马鼻镇"},{"code":"350122110","name":"官坂镇"},{"code":"350122111","name":"筱埕镇"},{"code":"350122112","name":"黄岐镇"},{"code":"350122113","name":"苔菉镇"},{"code":"350122114","name":"浦口镇"},{"code":"350122115","name":"坑园镇"},{"code":"350122200","name":"潘渡乡"},{"code":"350122201","name":"江南乡"},{"code":"350122202","name":"蓼沿乡"},{"code":"350122203","name":"安凯乡"},{"code":"350122204","name":"下宫乡"},{"code":"350122205","name":"小沧畲族乡"},{"code":"350122400","name":"马祖乡"}]