[{"code":"430103002","name":"坡子街街道"},{"code":"430103004","name":"城南路街道"},{"code":"430103005","name":"裕南街街道"},{"code":"430103006","name":"金盆岭街道"},{"code":"430103007","name":"新开铺街道"},{"code":"430103008","name":"青园街道"},{"code":"430103009","name":"桂花坪街道"},{"code":"430103010","name":"赤岭路街道"},{"code":"430103011","name":"文源街道"},{"code":"430103012","name":"先锋街道"},{"code":"430103013","name":"黑石铺街道"},{"code":"430103014","name":"大托铺街道"},{"code":"430103015","name":"暮云街道"},{"code":"430103016","name":"南托街道"}]