[{"code":"440281001","name":"乐城街道"},{"code":"440281102","name":"北乡镇"},{"code":"440281103","name":"九峰镇"},{"code":"440281104","name":"廊田镇"},{"code":"440281105","name":"长来镇"},{"code":"440281106","name":"梅花镇"},{"code":"440281107","name":"三溪镇"},{"code":"440281108","name":"坪石镇"},{"code":"440281110","name":"黄圃镇"},{"code":"440281111","name":"五山镇"},{"code":"440281112","name":"两江镇"},{"code":"440281113","name":"沙坪镇"},{"code":"440281114","name":"云岩镇"},{"code":"440281115","name":"秀水镇"},{"code":"440281117","name":"大源镇"},{"code":"440281118","name":"庆云镇"},{"code":"440281119","name":"白石镇"},{"code":"440281451","name":"坪石"},{"code":"440281452","name":"梅田"}]