[{"code":"510116001","name":"东升街道办"},{"code":"510116002","name":"西航港街道办"},{"code":"510116003","name":"华阳镇街道办"},{"code":"510116004","name":"中和街道办"},{"code":"510116005","name":"九江街道"},{"code":"510116006","name":"黄甲街道"},{"code":"510116007","name":"公兴街道"},{"code":"510116008","name":"协和街道"},{"code":"510116101","name":"太平镇"},{"code":"510116102","name":"永兴镇"},{"code":"510116106","name":"籍田镇"},{"code":"510116107","name":"正兴镇"},{"code":"510116108","name":"彭镇"},{"code":"510116109","name":"大林镇"},{"code":"510116110","name":"煎茶镇"},{"code":"510116111","name":"黄龙溪镇"},{"code":"510116112","name":"永安镇"},{"code":"510116115","name":"黄水镇"},{"code":"510116116","name":"金桥镇"},{"code":"510116119","name":"胜利镇"},{"code":"510116120","name":"新兴镇"},{"code":"510116121","name":"兴隆镇"},{"code":"510116122","name":"万安镇"},{"code":"510116123","name":"白沙镇"},{"code":"510116124","name":"三星镇"},{"code":"510116125","name":"合江镇"}]