[{"code":"610602001","name":"宝塔山街道"},{"code":"610602002","name":"南市街道"},{"code":"610602003","name":"凤凰山街道"},{"code":"610602004","name":"枣园街道"},{"code":"610602005","name":"桥沟街道"},{"code":"610602102","name":"河庄坪镇"},{"code":"610602103","name":"李渠镇"},{"code":"610602104","name":"姚店镇"},{"code":"610602105","name":"青化砭镇"},{"code":"610602106","name":"蟠龙镇"},{"code":"610602107","name":"柳林镇"},{"code":"610602108","name":"南泥湾镇"},{"code":"610602109","name":"临镇"},{"code":"610602110","name":"甘谷驿镇"},{"code":"610602200","name":"川口乡"},{"code":"610602202","name":"冯庄乡"},{"code":"610602205","name":"麻洞川乡"},{"code":"610602208","name":"万花山乡"}]