[{"code":"610825001","name":"定边街道"},{"code":"610825101","name":"贺圈镇"},{"code":"610825102","name":"红柳沟镇"},{"code":"610825103","name":"砖井镇"},{"code":"610825104","name":"白泥井镇"},{"code":"610825105","name":"安边镇"},{"code":"610825106","name":"堆子梁镇"},{"code":"610825107","name":"白湾子镇"},{"code":"610825108","name":"姬塬镇"},{"code":"610825109","name":"杨井镇"},{"code":"610825110","name":"新安边镇"},{"code":"610825111","name":"张崾先镇"},{"code":"610825112","name":"樊学镇"},{"code":"610825113","name":"盐场堡镇"},{"code":"610825114","name":"郝滩镇"},{"code":"610825202","name":"石洞沟乡"},{"code":"610825204","name":"油房庄乡"},{"code":"610825207","name":"冯地坑乡"},{"code":"610825210","name":"学庄乡"}]